aeon_neuro/__init__.py
aeon_neuro/benchmarking/__init__.py
aeon_neuro/benchmarking/experiments.py
aeon_neuro/data/Blink/Blink.gif
aeon_neuro/data/Blink/Blink.ts
aeon_neuro/data/Blink/Blink.txt
aeon_neuro/data/Blink/Blink_TEST.ts
aeon_neuro/data/Blink/Blink_TRAIN.ts
aeon_neuro/data/EyesOpenShut/EyesOpenShut.txt
aeon_neuro/data/EyesOpenShut/EyesOpenShut_TEST.ts
aeon_neuro/data/EyesOpenShut/EyesOpenShut_TRAIN.ts
aeon_neuro/data/FingerMovements/FingerMovements.txt
aeon_neuro/data/FingerMovements/FingerMovements_TEST.ts
aeon_neuro/data/FingerMovements/FingerMovements_TRAIN.ts
aeon_neuro/data/HandMovementDirection/HandMovementDirection.txt
aeon_neuro/data/HandMovementDirection/HandMovementDirection_TEST.ts
aeon_neuro/data/HandMovementDirection/HandMovementDirection_TRAIN.ts
aeon_neuro/data/SelfRegulationSCP1/SelfRegulationSCP1.txt
aeon_neuro/data/SelfRegulationSCP1/SelfRegulationSCP1_TEST.ts
aeon_neuro/data/SelfRegulationSCP1/SelfRegulationSCP1_TRAIN.ts
aeon_neuro/data/SelfRegulationSCP2/SelfRegulationSCP2.txt
aeon_neuro/data/SelfRegulationSCP2/SelfRegulationSCP2_TEST.ts
aeon_neuro/data/SelfRegulationSCP2/SelfRegulationSCP2_TRAIN.ts
aeon_neuro/data/auxiliary/Blink.json
aeon_neuro/data/auxiliary/EyesOpenShut.json
aeon_neuro/data/auxiliary/FaceDetection.json
aeon_neuro/data/auxiliary/FingerMovements.json
aeon_neuro/data/auxiliary/HandMovementDirection.json
aeon_neuro/data/auxiliary/MotorImagery.json
aeon_neuro/data/auxiliary/SelfRegulationSCP1.json
aeon_neuro/data/auxiliary/SelfRegulationSCP2.json
aeon_neuro/data/example_dataset/README
aeon_neuro/data/example_dataset/dataset_description.json
aeon_neuro/data/example_dataset/participants.json
aeon_neuro/data/example_dataset/participants.tsv
aeon_neuro/data/example_dataset/sub-01/ses-01/sub-01_ses-01_scans.tsv
aeon_neuro/data/example_dataset/sub-01/ses-01/eeg/sub-01_ses-01_task-EC_run-01_channels.tsv
aeon_neuro/data/example_dataset/sub-01/ses-01/eeg/sub-01_ses-01_task-EC_run-01_eeg.eeg
aeon_neuro-0.0.1.dist-info/LICENSE
aeon_neuro-0.0.1.dist-info/METADATA
aeon_neuro-0.0.1.dist-info/WHEEL
aeon_neuro-0.0.1.dist-info/top_level.txt
aeon_neuro-0.0.1.dist-info/zip-safe
aeon_neuro-0.0.1.dist-info/RECORD
