Metadata-Version: 2.1
Name: aeon-neuro
Version: 0.0.1
Summary: A package for ECG and EEG time series analysis built on the aeon toolkit.
Author-email: aeon developers <contact@aeon-toolkit.org>
Maintainer-email: aeon developers <contact@aeon-toolkit.org>
License: BSD 3-Clause License
Project-URL: Homepage, https://www.aeon-toolkit.org
Project-URL: Repository, https://github.com/aeon-toolkit/aeon-neuro
Project-URL: Download, https://pypi.org/project/aeon-neuro/#files
Keywords: data-science,machine-learning,time-series,time-series-analysis,neuroscience,ECG,EEG
Classifier: Intended Audience :: Science/Research
Classifier: Intended Audience :: Developers
Classifier: License :: OSI Approved :: BSD License
Classifier: Programming Language :: Python
Classifier: Topic :: Software Development
Classifier: Topic :: Scientific/Engineering
Classifier: Development Status :: 5 - Production/Stable
Classifier: Operating System :: Microsoft :: Windows
Classifier: Operating System :: POSIX
Classifier: Operating System :: Unix
Classifier: Operating System :: MacOS
Classifier: Programming Language :: Python :: 3
Classifier: Programming Language :: Python :: 3.8
Classifier: Programming Language :: Python :: 3.9
Classifier: Programming Language :: Python :: 3.10
Classifier: Programming Language :: Python :: 3.11
Classifier: Programming Language :: Python :: 3.12
Requires-Python: <3.13,>=3.8
License-File: LICENSE
Requires-Dist: aeon <0.11.0
Requires-Dist: mne
Requires-Dist: pyprep
Provides-Extra: all_extras
Requires-Dist: aeon[all_extras] ; extra == 'all_extras'
Provides-Extra: binder
Requires-Dist: aeon[binder] ; extra == 'binder'
Provides-Extra: dev
Requires-Dist: aeon[dev] ; extra == 'dev'
Provides-Extra: docs
Requires-Dist: aeon[docs] ; extra == 'docs'
